LICENSE.txt
README.md
setup.py
TheAmino/TheAmino.py
TheAmino/__init__.py
TheAmino/acm.py
TheAmino/client.py
TheAmino/socket.py
TheAmino/sub_client.py
TheAmino.egg-info/PKG-INFO
TheAmino.egg-info/SOURCES.txt
TheAmino.egg-info/dependency_links.txt
TheAmino.egg-info/requires.txt
TheAmino.egg-info/top_level.txt
TheAmino/asyncfix/__init__.py
TheAmino/asyncfix/acm.py
TheAmino/asyncfix/client.py
TheAmino/asyncfix/socket.py
TheAmino/asyncfix/sub_client.py
TheAmino/lib/__init__.py
TheAmino/lib/util/__init__.py
TheAmino/lib/util/exceptions.py
TheAmino/lib/util/headers.py
TheAmino/lib/util/helpers.py
TheAmino/lib/util/objects.py