Metadata-Version: 2.1
Name: TheAmino
Version: 1.0.0
Summary: An API for amino bot using Python
Home-page: https://github.com/NotCyberCodex/TheAmino
Author: Codex and Arjun
Keywords: python,bot,aminobot,theamino
Classifier: Development Status :: 1 - Planning
Classifier: Intended Audience :: Developers
Classifier: Programming Language :: Python :: 3
Classifier: Operating System :: Unix
Classifier: Operating System :: MacOS :: MacOS X
Classifier: Operating System :: Microsoft :: Windows
Requires-Python: >=3.10
License-File: LICENSE.txt
